cornflow_client/__init__.py
cornflow_client/constants.py
cornflow_client/cornflow_client.py
cornflow_client/raw_cornflow_client.py
cornflow_client/airflow/__init__.py
cornflow_client/airflow/api.py
cornflow_client/airflow/dag_utilities.py
cornflow_client/core/__init__.py
cornflow_client/core/application.py
cornflow_client/core/experiment.py
cornflow_client/core/instance.py
cornflow_client/core/instance_solution.py
cornflow_client/core/read_tools.py
cornflow_client/core/solution.py
cornflow_client/core/tools.py
cornflow_client/data/__init__.py
cornflow_client/data/empty_schema.json
cornflow_client/data/pulp_json_schema.json
cornflow_client/data/schema_validator.json
cornflow_client/data/solver_config.json
cornflow_client/data/vrp_solution_schema.json
cornflow_client/schema/__init__.py
cornflow_client/schema/dictSchema.py
cornflow_client/schema/dict_functions.py
cornflow_client/schema/manager.py
cornflow_client/schema/tools.py
cornflow_client/tests/__init__.py
cornflow_client/tests/const.py
cornflow_client/tests/data/__init__.py
cornflow_client/tests/data/data_input_bad.json
cornflow_client/tests/data/data_schema.json
cornflow_client/tests/data/endpoints_access.json
cornflow_client/tests/data/endpoints_methods.json
cornflow_client/tests/data/gc_input.json
cornflow_client/tests/data/gc_output.json
cornflow_client/tests/data/graph_coloring_input.json
cornflow_client/tests/data/graph_coloring_output.json
cornflow_client/tests/data/hk_data_input.json
cornflow_client/tests/data/hk_data_schema.json
cornflow_client/tests/data/hk_solution_schema.json
cornflow_client/tests/data/instance-hackathon2.json
cornflow_client/tests/data/name_problem_schema.json
cornflow_client/tests/data/pulp_example_data.json
cornflow_client/tests/data/schema_with_fk.json
cornflow_client/tests/data/schema_without_fk.json
cornflow_client/tests/data/test_mps.mps
cornflow_client/tests/data/xl_with_access.xlsx
cornflow_client/tests/data/xl_with_fk.xlsx
cornflow_client/tests/data/xl_with_methods.xlsx
cornflow_client-1.2.5.dist-info/licenses/LICENSE
cornflow_client-1.2.5.dist-info/METADATA
cornflow_client-1.2.5.dist-info/WHEEL
cornflow_client-1.2.5.dist-info/top_level.txt
cornflow_client-1.2.5.dist-info/RECORD
