Metadata-Version: 2.4
Name: cornflow-client
Version: 1.2.5
Summary: Client to connect to a cornflow server
Home-page: https://github.com/baobabsoluciones/cornflow
Author: baobab soluciones
Author-email: sistemas@baobabsoluciones.es
Classifier: Programming Language :: Python :: 3
Classifier: License :: OSI Approved :: Apache Software License
Classifier: Operating System :: OS Independent
Classifier: Development Status :: 5 - Production/Stable
Requires-Python: >=3.9
License-File: LICENSE
Requires-Dist: requests<=2.32.4
Requires-Dist: genson<=1.2.2
Requires-Dist: jsonschema<=4.21.1
Requires-Dist: marshmallow<=3.20.2
Requires-Dist: pytups<=0.86.2
Requires-Dist: ortools<=9.8.3296
Requires-Dist: PuLP<=2.9.0
Dynamic: author
Dynamic: author-email
Dynamic: classifier
Dynamic: description
Dynamic: description-content-type
Dynamic: home-page
Dynamic: license-file
Dynamic: requires-dist
Dynamic: requires-python
Dynamic: summary
